lvmbeat/__init__.py
lvmbeat/__main__.py
lvmbeat/actor.py
lvmbeat/config.yaml
lvmbeat/heartbeats.py
lvmbeat/monitor.py
lvmbeat/tools.py
lvmbeat-0.2.2.dist-info/METADATA
lvmbeat-0.2.2.dist-info/WHEEL
lvmbeat-0.2.2.dist-info/entry_points.txt
lvmbeat-0.2.2.dist-info/licenses/LICENSE.md
lvmbeat-0.2.2.dist-info/RECORD
